EL467/project/design.sv
module elevator(input [3:0] req_floor,input clk);
  
  reg floor_status[7:0];//binary list to represent floor_status
  reg [2:0] state=2'b00;
  reg[3:0] up_floor=4'b0000;//represents highest requested floor
  reg[3:0] down_floor=4'b0000;//represents lowest requested floor
  reg[3:0] target_floor=4'b0000;//target floor
  reg[3:0] curr_floor=4'b0000;// current floor
  always @ (*) //intial condition for elevator
    begin
      if(down_floor==up_floor && target_floor==up_floor)
        begin
          target_floor=req_floor;
        end
    end
  always @ (req_floor)//updating floor_status list
  begin
    floor_status[req_floor]=1'b1;//1 represents that the floor is in the list
  end
  
  always @ (*) begin //updating up_floor and down_floor on every request
      if(req_floor>up_floor)
        begin
          up_floor=req_floor;
        end
      else if(req_floor<down_floor)
        begin
          down_floor=req_floor;
        end
     end
  always @(posedge clk) begin
     if(up_floor==0 && down_floor==0 && curr_floor==0)
      begin
        state=2'b00;
        target_floor=0;
      end
  case (state)
    //2'b11 ==> moving up
    //2'b01 ==> moving down
    //2'b00 ==> idel
    // idle state: wait for a target floor
    2'b00:
      if(target_floor>curr_floor)//if target_floor is above curr_floor then set state=2'b11
          begin
            state=2'b11;
          end
      else if(target_floor<curr_floor)
          begin
            state=2'b01;
          end
      else
        state=2'b00;

    2'b11:
      if(floor_status[curr_floor]==1)//move up until last floor reached
          begin
            #10
            floor_status[curr_floor]=0;
          end
      else if(curr_floor==target_floor || curr_floor==7)
          begin
            target_floor=down_floor;
            up_floor=0;
            state=2'b01;
            curr_floor--;
          end  
      else
        begin
          state=2'b11;
          curr_floor++;
        end
 
    2'b01://move down until down floor reached
        if(floor_status[curr_floor]==1)
         begin
            #10
            floor_status[curr_floor]=0;
         end
        else if(curr_floor==target_floor || curr_floor==0)
            begin
              target_floor=up_floor;
              down_floor=0;
              state=2'b11;
              curr_floor++;
            end
        else
          begin
            state=2'b01;
            curr_floor--;
          end     
  endcase
end

      
endmodule

EL467/project/testbench.sv
module testbench;

// input signals
  reg clk;
  reg [3:0] req_floor;

// output signals


// instantiate the elevator controller
  elevator elevatorcontroller(req_floor,clk);

// test bench code
initial begin
  // set initial values for the input signals
  $dumpfile("abc.vcd");
  $dumpvars(0,testbench);
  clk = 0;
 
  req_floor = 4'b0110;

  // run the test for 100 clock cycles
  #20;

  // set the target floor to 3
  req_floor = 4'b001;

  // run the test for 100 clock cycles
  #10;

  // set the target floor to 1
  req_floor = 4'b0101;

  // run the test for 100 clock cycles
  #10;

  // set the target floor to 0
  req_floor = 4'b0000;

  // run the test for 100 clock cycles
  #100;
  //targetFloor=4'b0100;
  #50;
  
  $finish;
end

// clock generator
always #5 clk = ~clk;

endmodule

EL467/project/waveform.vcd
$date
	Tue Dec 13 16:21:39 2022
$end
$version
	Icarus Verilog
$end
$timescale
	1s
$end
$scope module testbench $end
$var reg 1 ! clk $end
$var reg 4 " req_floor [3:0] $end
$scope module elevatorcontroller $end
$var wire 1 ! clk $end
$var wire 4 # req_floor [3:0] $end
$var reg 4 $ curr_floor [3:0] $end
$var reg 4 % down_floor [3:0] $end
$var reg 3 & state [2:0] $end
$var reg 4 ' target_floor [3:0] $end
$var reg 4 ( up_floor [3:0] $end
$upscope $end
$upscope $end
$enddefinitions $end
#0
$dumpvars
b110 (
b110 '
b0 &
b0 %
b0 $
b110 #
b110 "
0!
$end
#5
b11 &
1!
#10
0!
#15
b1 $
1!
#20
0!
b1 "
b1 #
#25
1!
#30
0!
b101 "
b101 #
#35
b10 $
1!
#40
0!
b0 "
b0 #
#45
b11 $
1!
#50
0!
#55
b100 $
1!
#60
0!
#65
b101 $
1!
#70
0!
#75
1!
#80
0!
#85
b110 $
1!
#90
0!
#95
1!
#100
0!
#105
b101 $
b1 &
b0 (
b0 '
1!
#110
0!
#115
b100 $
1!
#120
0!
#125
b11 $
1!
#130
0!
#135
b10 $
1!
#140
0!
#145
b1 $
1!
#150
0!
#155
b0 $
1!
#160
0!
#165
b0 &
1!
